kmstool/__init__.py
kmstool/cli.py
kmstool/files.py
kmstool/kms.py
kmstool-0.7.0.dist-info/DESCRIPTION.rst
kmstool-0.7.0.dist-info/entry_points.txt
kmstool-0.7.0.dist-info/METADATA
kmstool-0.7.0.dist-info/metadata.json
kmstool-0.7.0.dist-info/RECORD
kmstool-0.7.0.dist-info/top_level.txt
kmstool-0.7.0.dist-info/WHEEL
