Metadata-Version: 2.0
Name: kmstool
Version: 0.7.0
Summary: A tool for storing and retrieving encrypted data using the AWS Key Management Service
Home-page: http://github.com/slank/kmstool
Author: Matthew Wedgwood
Author-email: mwedgwood@gmail.com
License: MIT
Keywords: amazon,aws,kms,encryption,key,management
Platform: UNKNOWN
Classifier: Development Status :: 3 - Alpha
Classifier: Topic :: Utilities
Classifier: License :: OSI Approved :: MIT License
Requires-Dist: botocore (>=0.80.0)
Requires-Dist: pycrypto (>=2.6.1)
